pyjangle_sqlite3/__init__.py
pyjangle_sqlite3/adapters_converters.py
pyjangle_sqlite3/event_handler_query_builder.py
pyjangle_sqlite3/initialize.py
pyjangle_sqlite3/pyjangle_sqlite3_error.py
pyjangle_sqlite3/sql_lite_event_repository.py
pyjangle_sqlite3/sql_lite_saga_repository.py
pyjangle_sqlite3/sql_lite_snapshot_repository.py
pyjangle_sqlite3/symbols.py
pyjangle_sqlite3/yield_results.py
pyjangle_sqlite3-0.1.0b0.dist-info/LICENSE
pyjangle_sqlite3-0.1.0b0.dist-info/METADATA
pyjangle_sqlite3-0.1.0b0.dist-info/WHEEL
pyjangle_sqlite3-0.1.0b0.dist-info/top_level.txt
pyjangle_sqlite3-0.1.0b0.dist-info/RECORD
